[
  {
    "username": "nigga",
    "password": "1",
    "userType": "TEACHER",
    "id": 1,
    "rooms": [
      1
    ]
  },
  {
    "username": "nigga2",
    "password": "1",
    "userType": "TEACHER",
    "id": 2,
    "rooms": [
      1
    ]
  },
  {
    "username": "reinis",
    "password": "1",
    "userType": "STUDENT",
    "id": 3,
    "rooms": [
      1
    ]
  },
  {
    "username": "sigma",
    "password": "1",
    "userType": "STUDENT",
    "id": 4,
    "rooms": [
      1
    ]
  },
  {
    "username": "nils",
    "password": "1",
    "userType": "STUDENT",
    "id": 5,
    "rooms": [
      1
    ]
  }
]